replay/UNKNOWN.egg-info/PKG-INFO
replay/UNKNOWN.egg-info/SOURCES.txt
replay/UNKNOWN.egg-info/dependency_links.txt
replay/UNKNOWN.egg-info/top_level.txt
replay/__init__.py
replay/__main__.py
replay/main.py
photo_replay-0.1.2.dist-info/entry_points.txt
photo_replay-0.1.2.dist-info/LICENSE
photo_replay-0.1.2.dist-info/WHEEL
photo_replay-0.1.2.dist-info/METADATA
photo_replay-0.1.2.dist-info/RECORD
