Metadata-Version: 2.1
Name: photo-replay
Version: 0.1.2
Summary: Makes a movie from a photo library
License: MIT
Author: Arvid Larsson
Author-email: arvla626@student.liu.se
Requires-Python: >=3.7,<4.0
Classifier: License :: OSI Approved :: MIT License
Classifier: Programming Language :: Python :: 3
Classifier: Programming Language :: Python :: 3.7
Classifier: Programming Language :: Python :: 3.8
Classifier: Programming Language :: Python :: 3.9
Requires-Dist: click (>=7.1.1,<8.0.0)
Requires-Dist: ffmpeg-python (>=0.2.0,<0.3.0)
Requires-Dist: opencv-python (>=4.4.0,<5.0.0)
Requires-Dist: pandas (>=1.0.3,<2.0.0)
Requires-Dist: pillow (>=7.1.1,<8.0.0)
Requires-Dist: regex (>=2020.4.4,<2021.0.0)
Requires-Dist: scandir (>=1.10.0,<2.0.0)
Requires-Dist: tqdm (>=4.55.0,<5.0.0)
